{"nodes":[{"pos":[32,68],"content":"Install ATA - Step 3 | Microsoft ATA","needQuote":true,"nodes":[{"content":"Install ATA - Step 3 | Microsoft ATA","pos":[0,36]}]},{"pos":[82,160],"content":"Step three of installing ATA helps you download the ATA Gateway setup package.","needQuote":true,"nodes":[{"content":"Step three of installing ATA helps you download the ATA Gateway setup package.","pos":[0,78]}]},{"pos":[489,540],"content":"<bpt id=\"p1\">*</bpt>Applies to: Advanced Threat Analytics version 1.7<ept id=\"p1\">*</ept>","source":"*Applies to: Advanced Threat Analytics version 1.7*"},{"content":"Install ATA - Step 3","pos":[546,566]},{"content":"<bpt id=\"p1\">[</bpt>« Step 2<ept id=\"p1\">](install-ata-step2.md)</ept><ph id=\"ph1\">\n</ph><bpt id=\"p2\">[</bpt>Step 4 »<ept id=\"p2\">](install-ata-step4.md)</ept>","pos":[597,662],"source":"[« Step 2](install-ata-step2.md)\n[Step 4 »](install-ata-step4.md)"},{"content":"Step 3.","pos":[667,674]},{"content":"Download the ATA Gateway setup package","pos":[675,713]},{"content":"After configuring the domain connectivity settings you can download the ATA Gateway setup package.","pos":[714,812]},{"content":"The ATA Gateway can be installed on a dedicated server or on a domain controller.","pos":[813,894]},{"content":"If you install it on a domain controller, it will be installed as an ATA Lightweight Gateway.","pos":[895,988]},{"content":"For more information on the ATA Lightweight Gateway, see <bpt id=\"p1\">[</bpt>ATA Architecture<ept id=\"p1\">](/advanced-threat-analytics/plan-design/ata-architecture)</ept>.","pos":[989,1122],"source":" For more information on the ATA Lightweight Gateway, see [ATA Architecture](/advanced-threat-analytics/plan-design/ata-architecture)."},{"content":"If this is the first time you are downloading an ATA Gateway, you will get the following screen:","pos":[1125,1221]},{"content":"ATA gateway configuration settings","pos":[1225,1259]},{"content":"If this is not your first time downloading an ATA Gateway, this welcome message will not appear.","pos":[1306,1402]},{"pos":[1406,1580],"content":"[!NOTE] \nTo reach the configuration screen later, click the **settings icon** (upper right corner) and select **Configuration**, then, under **System**, click **Gateways**.","leadings":["","> "],"nodes":[{"content":"To reach the configuration screen later, click the <bpt id=\"p1\">**</bpt>settings icon<ept id=\"p1\">**</ept> (upper right corner) and select <bpt id=\"p2\">**</bpt>Configuration<ept id=\"p2\">**</ept>, then, under <bpt id=\"p3\">**</bpt>System<ept id=\"p3\">**</ept>, click <bpt id=\"p4\">**</bpt>Gateways<ept id=\"p4\">**</ept>.","pos":[9,172],"source":"To reach the configuration screen later, click the **settings icon** (upper right corner) and select **Configuration**, then, under **System**, click **Gateways**."}]},{"pos":[1588,1623],"content":"Click <bpt id=\"p1\">**</bpt>\"Download Gateway Setup\"<ept id=\"p1\">**</ept>.","source":"Click **\"Download Gateway Setup\"**."},{"content":"Save the package locally.","pos":[1628,1653]},{"content":"Copy the package to the dedicated server or domain controller onto which you are installing the ATA Gateway.","pos":[1658,1766]},{"content":"Alternatively, you can open the ATA Console from the dedicated server or domain controller and skip this step.","pos":[1767,1877]},{"content":"The zip file includes the following:","pos":[1879,1915]},{"content":"ATA Gateway installer","pos":[1921,1942]},{"content":"Configuration setting file with the required information to connect to the ATA Center","pos":[1948,2033]},{"content":"<bpt id=\"p1\">[</bpt>« Step 2<ept id=\"p1\">](install-ata-step2.md)</ept><ph id=\"ph1\">\n</ph><bpt id=\"p2\">[</bpt>Step 4 »<ept id=\"p2\">](install-ata-step4.md)</ept>","pos":[2065,2130],"source":"[« Step 2](install-ata-step2.md)\n[Step 4 »](install-ata-step4.md)"},{"content":"See Also","pos":[2135,2143]},{"pos":[2147,2243],"content":"<bpt id=\"p1\">[</bpt>Check out the ATA forum!<ept id=\"p1\">](https://social.technet.microsoft.com/Forums/security/home?forum=mata)</ept>","source":"[Check out the ATA forum!](https://social.technet.microsoft.com/Forums/security/home?forum=mata)"},{"pos":[2246,2305],"content":"<bpt id=\"p1\">[</bpt>Configure event collection<ept id=\"p1\">](configure-event-collection.md)</ept>","source":"[Configure event collection](configure-event-collection.md)"},{"pos":[2308,2385],"content":"<bpt id=\"p1\">[</bpt>ATA prerequisites<ept id=\"p1\">](/advanced-threat-analytics/plan-design/ata-prerequisites)</ept>","source":"[ATA prerequisites](/advanced-threat-analytics/plan-design/ata-prerequisites)"}],"content":"---\n# required metadata\n\ntitle: Install ATA - Step 3 | Microsoft ATA\ndescription: Step three of installing ATA helps you download the ATA Gateway setup package.\nkeywords:\nauthor: rkarlin\nmanager: mbaldwin\nms.date: 08/24/2016\nms.topic: get-started-article\nms.prod:\nms.service: advanced-threat-analytics\nms.technology:\nms.assetid: 7fb024e6-297a-4ad9-b962-481bb75a0ba3\n\n# optional metadata\n\n#ROBOTS:\n#audience:\n#ms.devlang:\nms.reviewer: bennyl\nms.suite: ems\n#ms.tgt_pltfrm:\n#ms.custom:\n\n---\n\n*Applies to: Advanced Threat Analytics version 1.7*\n\n\n\n# Install ATA - Step 3\n\n>[!div class=\"step-by-step\"]\n[« Step 2](install-ata-step2.md)\n[Step 4 »](install-ata-step4.md)\n\n## Step 3. Download the ATA Gateway setup package\nAfter configuring the domain connectivity settings you can download the ATA Gateway setup package. The ATA Gateway can be installed on a dedicated server or on a domain controller. If you install it on a domain controller, it will be installed as an ATA Lightweight Gateway. For more information on the ATA Lightweight Gateway, see [ATA Architecture](/advanced-threat-analytics/plan-design/ata-architecture). \n\nIf this is the first time you are downloading an ATA Gateway, you will get the following screen:\n\n![ATA gateway configuration settings](media/ATA_1.7-welcome-download-gateway.PNG)\n\nIf this is not your first time downloading an ATA Gateway, this welcome message will not appear.\n\n> [!NOTE] \n> To reach the configuration screen later, click the **settings icon** (upper right corner) and select **Configuration**, then, under **System**, click **Gateways**.  \n\n1.  Click **\"Download Gateway Setup\"**.\n2.  Save the package locally.\n3.  Copy the package to the dedicated server or domain controller onto which you are installing the ATA Gateway. Alternatively, you can open the ATA Console from the dedicated server or domain controller and skip this step.\n\nThe zip file includes the following:\n\n-   ATA Gateway installer\n\n-   Configuration setting file with the required information to connect to the ATA Center\n\n\n>[!div class=\"step-by-step\"]\n[« Step 2](install-ata-step2.md)\n[Step 4 »](install-ata-step4.md)\n\n## See Also\n\n- [Check out the ATA forum!](https://social.technet.microsoft.com/Forums/security/home?forum=mata)\n- [Configure event collection](configure-event-collection.md)\n- [ATA prerequisites](/advanced-threat-analytics/plan-design/ata-prerequisites)\n"}