{"nodes":[{"pos":[13,33],"content":"DSC Package Resource","needQuote":true,"nodes":[{"content":"DSC Package Resource","pos":[0,20]}]},{"pos":[66,80],"content":"powershell,DSC","needQuote":true,"nodes":[{"content":"powershell,DSC","pos":[0,14]}]},{"content":"DSC Package Resource","pos":[178,198]},{"content":"Applies To: Windows PowerShell 4.0, Windows PowerShell 5.0","pos":[202,260]},{"pos":[262,465],"content":"The <bpt id=\"p1\">**</bpt>Package<ept id=\"p1\">**</ept> resource in Windows PowerShell Desired State Configuration (DSC) provides a mechanism to install or uninstall packages, such as Windows Installer and setup.exe packages, on a target node.","source":"The **Package** resource in Windows PowerShell Desired State Configuration (DSC) provides a mechanism to install or uninstall packages, such as Windows Installer and setup.exe packages, on a target node."},{"content":"Syntax","pos":[470,476]},{"content":"Properties","pos":[793,803]},{"content":"Property","pos":[807,815]},{"content":"Description","pos":[820,831]},{"content":"Name","pos":[850,854]},{"content":"Indicates the name of the package for which you want to ensure a specific state.","pos":[856,936]},{"content":"Path","pos":[941,945]},{"content":"Indicates the path where the package resides.","pos":[947,992]},{"content":"ProductId","pos":[997,1006]},{"content":"Indicates the product ID that uniquely identifies the package.","pos":[1008,1070]},{"content":"Arguments","pos":[1075,1084]},{"content":"Lists a string of arguments that will be passed to the package exactly as provided.","pos":[1086,1169]},{"content":"Credential","pos":[1174,1184]},{"content":"Provides access to the package on a remote source.","pos":[1186,1236]},{"content":"This property is not used to install the package.","pos":[1237,1286]},{"content":"The package is always installed on the local system.","pos":[1287,1339]},{"content":"Ensure","pos":[1344,1350]},{"content":"Indicates if the package is installed.","pos":[1352,1390]},{"content":"Set this property to \"Absent\" to ensure the package is not installed (or uninstall the package if it is installed).","pos":[1391,1506]},{"content":"Set it to \"Present\" (the default value) to ensure the package is installed.","pos":[1507,1582]},{"content":"LogPath","pos":[1587,1594]},{"content":"Indicates the full path where you want the provider to save a log file to install or uninstall the package.","pos":[1596,1703]},{"content":"DependsOn","pos":[1708,1717]},{"content":"Indicates that the configuration of another resource must run before this resource is configured.","pos":[1720,1817]},{"content":"For example, if the ID of the resource configuration script block that you want to run first is <bpt id=\"p1\">**</bpt>ResourceName<ept id=\"p1\">**</ept> and its type is <bpt id=\"p2\">**</bpt>ResourceType<ept id=\"p2\">**</ept>, the syntax for using this property is `DependsOn = \"[ResourceType]ResourceName\"``.","pos":[1818,2047],"source":" For example, if the ID of the resource configuration script block that you want to run first is **ResourceName** and its type is **ResourceType**, the syntax for using this property is `DependsOn = \"[ResourceType]ResourceName\"``."},{"content":"ReturnCode","pos":[2052,2062]},{"content":"Indicates the expected return code.","pos":[2064,2099]},{"content":"If the actual return code does not match the expected value provided here, the configuration will return an error.","pos":[2100,2214]},{"content":"Example","pos":[2221,2228]},{"content":"This example runs the .msi installer that is located at the specified path and has the specified product ID.","pos":[2230,2338]}],"content":"---\ntitle:   DSC Package Resource\nms.date:  2016-05-16\nkeywords:  powershell,DSC\ndescription:  \nms.topic:  article\nauthor:  eslesar\nmanager:  dongill\nms.prod:  powershell\n---\n\n# DSC Package Resource\n\n> Applies To: Windows PowerShell 4.0, Windows PowerShell 5.0\n\nThe **Package** resource in Windows PowerShell Desired State Configuration (DSC) provides a mechanism to install or uninstall packages, such as Windows Installer and setup.exe packages, on a target node.\n\n## Syntax\n\n```\nPackage [string] #ResourceName\n{\n    Name = [string]\n    Path = [string]\n    ProductId = [string]\n    [ Arguments = [string] ]\n    [ Credential = [PSCredential] ]\n    [ Ensure = [string] { Absent | Present }  ]\n    [ LogPath = [string] ]\n    [ DependsOn = [string[]] ]\n    [ ReturnCode = [UInt32[]] ]\n}\n```\n\n## Properties\n|  Property  |  Description   | \n|---|---| \n| Name| Indicates the name of the package for which you want to ensure a specific state.| \n| Path| Indicates the path where the package resides.| \n| ProductId| Indicates the product ID that uniquely identifies the package.| \n| Arguments| Lists a string of arguments that will be passed to the package exactly as provided.| \n| Credential| Provides access to the package on a remote source. This property is not used to install the package. The package is always installed on the local system.| \n| Ensure| Indicates if the package is installed. Set this property to \"Absent\" to ensure the package is not installed (or uninstall the package if it is installed). Set it to \"Present\" (the default value) to ensure the package is installed.| \n| LogPath| Indicates the full path where you want the provider to save a log file to install or uninstall the package.| \n| DependsOn | Indicates that the configuration of another resource must run before this resource is configured. For example, if the ID of the resource configuration script block that you want to run first is **ResourceName** and its type is **ResourceType**, the syntax for using this property is `DependsOn = \"[ResourceType]ResourceName\"``.| \n| ReturnCode| Indicates the expected return code. If the actual return code does not match the expected value provided here, the configuration will return an error.| \n\n## Example\n\nThis example runs the .msi installer that is located at the specified path and has the specified product ID.\n\n```powershell\nConfiguration PackageTest\n{\n    Package PackageExample\n    {\n        Ensure      = \"Present\"  # You can also set Ensure to \"Absent\"\n        Path        = \"$Env:SystemDrive\\TestFolder\\TestProject.msi\"\n        Name        = \"TestPackage\"\n        ProductId   = \"ACDDCDAF-80C6-41E6-A1B9-8ABD8A05027E\"\n    } \n}\n```\n\n"}