{"nodes":[{"pos":[32,88],"content":"How your Android users get their apps | Microsoft Intune","needQuote":true,"nodes":[{"content":"How your Android users get their apps | Microsoft Intune","pos":[0,56]}]},{"pos":[102,156],"content":"Methods for making Android apps available to end users","needQuote":true,"nodes":[{"content":"Methods for making Android apps available to end users","pos":[0,54]}]},{"content":"How your Android users get their apps","pos":[471,508]},{"content":"Use this information to understand how and where your Android end users get the apps that you distribute through Microsoft Intune.","pos":[509,639]},{"content":"The information can be different for native Android devices versus Samsung Knox devices.","pos":[640,728]},{"content":"Native (non-Samsung Knox) Android devices","pos":[733,774]},{"content":"App type","pos":[778,786]},{"content":"Line-of-business (LOB) apps","pos":[789,816]},{"content":"Play Store apps","pos":[819,834]},{"content":"Available apps","pos":[879,893]},{"content":"Users tap <bpt id=\"p1\">**</bpt>install<ept id=\"p1\">**</ept> in the Company Portal.","pos":[901,945],"source":"Users tap **install** in the Company Portal."},{"content":"A notification appears, which users then tap to start the installation.","pos":[946,1017]},{"content":"After the installation is successful, the notification disappears.","pos":[1018,1084]},{"content":"Users tap the app in the Company Portal and are taken to an app page in the Play Store, where they can start the installation.","pos":[1087,1213]},{"content":"Required apps","pos":[1217,1230]},{"content":"Users are shown a notification, which they cannot dismiss, indicating that they need to install an app.","pos":[1238,1341]},{"content":"Users tap the notification to start the installation.","pos":[1342,1395]},{"content":"After the installation is successful, the notification disappears.","pos":[1396,1462]},{"content":"Users are shown a notification, which they cannot dismiss, indicating that they need to install an app.","pos":[1468,1571]},{"content":"Users tap the notification and are taken to an app page in the Play Store, where they can start the installation.","pos":[1572,1685]},{"content":"After the installation is successful, the notification disappears.","pos":[1686,1752]},{"content":"Samsung Knox Android devices","pos":[1759,1787]},{"content":"App type","pos":[1791,1799]},{"content":"Line-of-business (LOB) apps","pos":[1802,1829]},{"content":"Play Store apps","pos":[1832,1847]},{"content":"Available apps","pos":[1892,1906]},{"content":"Users tap <bpt id=\"p1\">**</bpt>install<ept id=\"p1\">**</ept> in the Company Portal.","pos":[1914,1958],"source":"Users tap **install** in the Company Portal."},{"content":"The app installs without further user intervention.","pos":[1959,2010]},{"content":"Users tap the app in the Company Portal and are taken to an app page in the Play Store, where they can start the installation.","pos":[2013,2139]},{"content":"Required apps","pos":[2143,2156]},{"content":"The app is installed without any user intervention.","pos":[2164,2215]},{"content":"Users are shown a notification, which they cannot dismiss, indicating that they need to install an app.","pos":[2221,2324]},{"content":"Users tap the notification and are taken to an app page in the Play Store, where they can start the installation.","pos":[2325,2438]},{"content":"After the installation is successful, the notification disappears.","pos":[2439,2505]},{"content":"Apps can be managed or unmanaged, as described below.","pos":[2509,2562]},{"content":"The process of making apps managed is the same for all types of Android devices.","pos":[2563,2643]},{"content":"<bpt id=\"p1\">**</bpt>Managed apps<ept id=\"p1\">**</ept> - Apps that can be managed through policies and that have been \"wrapped\" by Intune or have been built with the Intune Mobile Application Management (MAM) Software Development Kit (SDK).","pos":[2645,2847],"source":"**Managed apps** - Apps that can be managed through policies and that have been \"wrapped\" by Intune or have been built with the Intune Mobile Application Management (MAM) Software Development Kit (SDK)."},{"content":"These apps can be managed by Intune, and application policies can be applied to them.","pos":[2848,2933]},{"content":"<bpt id=\"p1\">**</bpt>Unmanaged apps<ept id=\"p1\">**</ept> - Apps that can be managed through policies and that have not been wrapped by Intune or that do not incorporate the Intune MAM SDK.","pos":[2935,3085],"source":"**Unmanaged apps** - Apps that can be managed through policies and that have not been wrapped by Intune or that do not incorporate the Intune MAM SDK."},{"content":"Application policies cannot be applied to these apps.","pos":[3086,3139]},{"content":"See also","pos":[3145,3153]},{"pos":[3154,3371],"content":"<bpt id=\"p1\">[</bpt>Add apps with Microsoft Intune<ept id=\"p1\">](/intune/deploy-use/add-apps)</ept><ph id=\"ph1\">\n</ph><bpt id=\"p2\">[</bpt>How your iOS users get their apps<ept id=\"p2\">](how-your-ios-users-get-their-apps.md)</ept><ph id=\"ph2\">\n</ph><bpt id=\"p3\">[</bpt>How your Windows users get their apps<ept id=\"p3\">](how-your-windows-users-get-their-apps.md)</ept>","source":"[Add apps with Microsoft Intune](/intune/deploy-use/add-apps)\n[How your iOS users get their apps](how-your-ios-users-get-their-apps.md)\n[How your Windows users get their apps](how-your-windows-users-get-their-apps.md)"}],"content":"---\n# required metadata\n\ntitle: How your Android users get their apps | Microsoft Intune\ndescription: Methods for making Android apps available to end users\nkeywords:\nauthor: Staciebarker\nmanager: angrobe\nms.date: 7/7/2016\nms.topic: article\nms.prod:\nms.service: microsoft-intune\nms.technology:\nms.assetid: f33d1684-b1b5-44f7-9aac-c6d5186a5d7c\n\n# optional metadata\n\n#ROBOTS:\n#audience:\n#ms.devlang:\nms.reviewer: jeffgilb\nms.suite: ems\n#ms.tgt_pltfrm:\n#ms.custom:\n\n---\n\n\n# How your Android users get their apps\nUse this information to understand how and where your Android end users get the apps that you distribute through Microsoft Intune. The information can be different for native Android devices versus Samsung Knox devices.\n\n## Native (non-Samsung Knox) Android devices\n\n| App type | Line-of-business (LOB) apps | Play Store apps  |\n| ------------- |-------------| -----|\n| Available apps      | Users tap **install** in the Company Portal. A notification appears, which users then tap to start the installation. After the installation is successful, the notification disappears. | Users tap the app in the Company Portal and are taken to an app page in the Play Store, where they can start the installation.|\n| Required apps      | Users are shown a notification, which they cannot dismiss, indicating that they need to install an app. Users tap the notification to start the installation. After the installation is successful, the notification disappears.    | Users are shown a notification, which they cannot dismiss, indicating that they need to install an app. Users tap the notification and are taken to an app page in the Play Store, where they can start the installation. After the installation is successful, the notification disappears. |\n\n## Samsung Knox Android devices\n\n| App type | Line-of-business (LOB) apps | Play Store apps  |\n| ------------- |-------------| -----|\n| Available apps      | Users tap **install** in the Company Portal. The app installs without further user intervention. | Users tap the app in the Company Portal and are taken to an app page in the Play Store, where they can start the installation.|\n| Required apps      | The app is installed without any user intervention.    | Users are shown a notification, which they cannot dismiss, indicating that they need to install an app. Users tap the notification and are taken to an app page in the Play Store, where they can start the installation. After the installation is successful, the notification disappears. |\n\nApps can be managed or unmanaged, as described below. The process of making apps managed is the same for all types of Android devices.\n\n**Managed apps** - Apps that can be managed through policies and that have been \"wrapped\" by Intune or have been built with the Intune Mobile Application Management (MAM) Software Development Kit (SDK). These apps can be managed by Intune, and application policies can be applied to them.\n\n**Unmanaged apps** - Apps that can be managed through policies and that have not been wrapped by Intune or that do not incorporate the Intune MAM SDK. Application policies cannot be applied to these apps.\n\n### See also\n[Add apps with Microsoft Intune](/intune/deploy-use/add-apps)\n[How your iOS users get their apps](how-your-ios-users-get-their-apps.md)\n[How your Windows users get their apps](how-your-windows-users-get-their-apps.md)\n"}