{"nodes":[{"pos":[32,93],"content":"Monitor MAM policies with Microsoft Intune | Microsoft Intune","needQuote":true,"nodes":[{"content":"Monitor MAM policies with Microsoft Intune | Microsoft Intune","pos":[0,61]}]},{"pos":[107,179],"content":"See how many users have the policy, drill down to find out more details.","needQuote":true,"nodes":[{"content":"See how many users have the policy, drill down to find out more details.","pos":[0,72]}]},{"content":"Monitor mobile app management policies with Microsoft Intune","pos":[496,556]},{"content":"After you have configured a MAM policy and applied it to the users, you can monitor the compliance status on the <bpt id=\"p1\">[</bpt>Azure portal<ept id=\"p1\">](https://portal.azure.com)</ept>.","pos":[557,711],"source":"After you have configured a MAM policy and applied it to the users, you can monitor the compliance status on the [Azure portal](https://portal.azure.com)."},{"content":"The Azure portal includes information about the users affected by the policy, the compliance status, and any issues that your end users might be experiencing.","pos":[712,870]},{"content":"Summary view","pos":[874,886]},{"pos":[887,1007],"content":"On the <bpt id=\"p1\">**</bpt>Intune mobile application management<ept id=\"p1\">**</ept> blade you can see a summary of the compliance status as described below:","source":"On the **Intune mobile application management** blade you can see a summary of the compliance status as described below:"},{"content":"Summary tile on the Intune mobile application management blade","pos":[1012,1074]},{"pos":[1132,1244],"content":"<bpt id=\"p1\">**</bpt>USERS:<ept id=\"p1\">**</ept> The total number of users in your company who are using the apps that are associated with the policy.","source":"**USERS:** The total number of users in your company who are using the apps that are associated with the policy."},{"pos":[1250,1353],"content":"<bpt id=\"p1\">**</bpt>MANAGED BY POLICY:<ept id=\"p1\">**</ept>- The number of users who have used at least one of the apps in the work context.","source":"**MANAGED BY POLICY:**- The number of users who have used at least one of the apps in the work context."},{"content":"<bpt id=\"p1\">**</bpt>NO POLICY:<ept id=\"p1\">**</ept> The number of users who are using the apps associated with the policy, but are not targeted by your policy.","pos":[1359,1481],"source":"**NO POLICY:** The number of users who are using the apps associated with the policy, but are not targeted by your policy."},{"content":"You may consider adding these users to your policy.","pos":[1483,1534]},{"content":"<bpt id=\"p1\">**</bpt>Flagged users:<ept id=\"p1\">**</ept> The number of users experiencing issues.","pos":[1538,1597],"source":"**Flagged users:** The number of users experiencing issues."},{"content":"Currently only users with jailbroken devices are reported under <bpt id=\"p1\">**</bpt>Flagged users<ept id=\"p1\">**</ept>.","pos":[1598,1680],"source":" Currently only users with jailbroken devices are reported under **Flagged users**."},{"content":"Detailed view","pos":[1686,1699]},{"pos":[1700,1819],"content":"You can get to the detailed view of the summary by clicking on the <bpt id=\"p1\">**</bpt>User status<ept id=\"p1\">**</ept> tile and the <bpt id=\"p2\">**</bpt>Flagged users<ept id=\"p2\">**</ept> tile.","source":"You can get to the detailed view of the summary by clicking on the **User status** tile and the **Flagged users** tile."},{"content":"User status","pos":[1825,1836]},{"content":"You can search for a single user and look at the compliance status for that user.","pos":[1837,1918]},{"content":"The <bpt id=\"p1\">**</bpt>App reporting<ept id=\"p1\">**</ept> blade displays the following information for a selected user:","pos":[1919,2002],"source":" The **App reporting** blade displays the following information for a selected user:"},{"content":"Device(s) that are associated with the user account","pos":[2005,2056]},{"content":"App(s) with MAM policy on the device","pos":[2059,2095]},{"content":"Status:","pos":[2098,2105]},{"pos":[2109,2225],"content":"<bpt id=\"p1\">**</bpt>Checked in:<ept id=\"p1\">**</ept> This means that the policy was deployed to the user, and app was used in work context at least once.","source":"**Checked in:** This means that the policy was deployed to the user, and app was used in work context at least once."},{"pos":[2229,2354],"content":"<bpt id=\"p1\">**</bpt>Not checked in:<ept id=\"p1\">**</ept> This means the policy was deployed to the user, but app has not been used in the work context since then.","source":"**Not checked in:** This means the policy was deployed to the user, but app has not been used in the work context since then."},{"pos":[2357,2531],"content":"[!NOTE]\nIf the user you searched for does not have the MAM policy deployed to them, you will see a message informing you that the user is not targeted for any app policies.","leadings":["","> "],"nodes":[{"content":"If the user you searched for does not have the MAM policy deployed to them, you will see a message informing you that the user is not targeted for any app policies.","pos":[8,172]}]},{"content":"To see the reporting for a user, follow these steps:","pos":[2533,2585]},{"pos":[2587,2732],"content":"<bpt id=\"p1\">**</bpt>Step 1:<ept id=\"p1\">**</ept>  To select a user, click on the Summary tile or choose the <bpt id=\"p2\">**</bpt>APP REPORTING BY USER<ept id=\"p2\">**</ept> option in the <bpt id=\"p3\">**</bpt>Settings<ept id=\"p3\">**</ept> blade as shown below:","source":"**Step 1:**  To select a user, click on the Summary tile or choose the **APP REPORTING BY USER** option in the **Settings** blade as shown below:"},{"content":"App reporting option on the settings blade","pos":[2736,2778]},{"content":"<bpt id=\"p1\">**</bpt>Step 2:<ept id=\"p1\">**</ept> This opens the <bpt id=\"p2\">**</bpt>App reporting<ept id=\"p2\">**</ept> blade.","pos":[2849,2900],"source":"**Step 2:** This opens the **App reporting** blade."},{"content":"Choose <bpt id=\"p1\">**</bpt>Select user<ept id=\"p1\">**</ept> to search for an Azure Active Directory user.","pos":[2901,2969],"source":" Choose **Select user** to search for an Azure Active Directory user."},{"content":"select user option on the App reporting blade","pos":[2973,3018]},{"pos":[3078,3194],"content":"<bpt id=\"p1\">**</bpt>Step 3:<ept id=\"p1\">**</ept> After selecting the user from the list, you will see the details of the compliance status for that user.","source":"**Step 3:** After selecting the user from the list, you will see the details of the compliance status for that user."},{"content":"App reporting details","pos":[3198,3219]},{"content":"Flagged users","pos":[3278,3291]},{"content":"The detailed view displays the error message, the app that was accessed when the error happened, the platform of the device, and a time stamp.","pos":[3292,3434]},{"content":"See also","pos":[3442,3450]},{"pos":[3451,3554],"content":"<bpt id=\"p1\">[</bpt>Manage data transfer between iOS apps<ept id=\"p1\">](manage-data-transfer-between-ios-apps-with-microsoft-intune.md)</ept>","source":"[Manage data transfer between iOS apps](manage-data-transfer-between-ios-apps-with-microsoft-intune.md)"},{"pos":[3556,3664],"content":"<bpt id=\"p1\">[</bpt>End user experience for MAM enabled app<ept id=\"p1\">](end-user-experience-for-mam-enabled-apps-with-microsoft-intune.md)</ept>","source":"[End user experience for MAM enabled app](end-user-experience-for-mam-enabled-apps-with-microsoft-intune.md)"}],"content":"---\n# required metadata\n\ntitle: Monitor MAM policies with Microsoft Intune | Microsoft Intune\ndescription: See how many users have the policy, drill down to find out more details.\nkeywords:\nauthor: karthikaraman\nmanager: angrobe\nms.date: 07/22/2016\nms.topic: article\nms.prod:\nms.service: microsoft-intune\nms.technology:\nms.assetid: d3aa6c74-6b5d-4b50-aa66-a040ec44393e\n\n# optional metadata\n\n#ROBOTS:\n#audience:\n#ms.devlang:\nms.reviewer: joglocke\nms.suite: ems\n#ms.tgt_pltfrm:\n#ms.custom:\n\n---\n\n# Monitor mobile app management policies with Microsoft Intune\nAfter you have configured a MAM policy and applied it to the users, you can monitor the compliance status on the [Azure portal](https://portal.azure.com). The Azure portal includes information about the users affected by the policy, the compliance status, and any issues that your end users might be experiencing.\n## Summary view\nOn the **Intune mobile application management** blade you can see a summary of the compliance status as described below:\n\n\n![Summary tile on the Intune mobile application management blade](../media/mam-azure-portal-user-status-summary.png)\n\n-   **USERS:** The total number of users in your company who are using the apps that are associated with the policy.\n\n-   **MANAGED BY POLICY:**- The number of users who have used at least one of the apps in the work context.\n\n-   **NO POLICY:** The number of users who are using the apps associated with the policy, but are not targeted by your policy.  You may consider adding these users to your policy.\n\n- **Flagged users:** The number of users experiencing issues. Currently only users with jailbroken devices are reported under **Flagged users**.\n\n\n## Detailed view\nYou can get to the detailed view of the summary by clicking on the **User status** tile and the **Flagged users** tile.\n\n### User status\nYou can search for a single user and look at the compliance status for that user. The **App reporting** blade displays the following information for a selected user:\n- Device(s) that are associated with the user account\n- App(s) with MAM policy on the device\n- Status:\n\n  **Checked in:** This means that the policy was deployed to the user, and app was used in work context at least once.\n\n  **Not checked in:** This means the policy was deployed to the user, but app has not been used in the work context since then.\n\n>[!NOTE]\n> If the user you searched for does not have the MAM policy deployed to them, you will see a message informing you that the user is not targeted for any app policies.\n\nTo see the reporting for a user, follow these steps:\n\n**Step 1:**  To select a user, click on the Summary tile or choose the **APP REPORTING BY USER** option in the **Settings** blade as shown below:\n\n![App reporting option on the settings blade](../media/mam-azure-portal-app-reporting-by-user-settings-blade.png)\n\n**Step 2:** This opens the **App reporting** blade. Choose **Select user** to search for an Azure Active Directory user.\n\n![select user option on the App reporting blade](../media/mam-azure-portal-app-reporting-select-user.png)\n\n**Step 3:** After selecting the user from the list, you will see the details of the compliance status for that user.\n\n![App reporting details](../media/mam-azure-portal-app-reporting-by-user.png)\n### Flagged users\nThe detailed view displays the error message, the app that was accessed when the error happened, the platform of the device, and a time stamp.  \n\n### See also\n[Manage data transfer between iOS apps](manage-data-transfer-between-ios-apps-with-microsoft-intune.md)\n\n[End user experience for MAM enabled app](end-user-experience-for-mam-enabled-apps-with-microsoft-intune.md)\n"}